{
  "contract_version": "practice_definition_registry_v1",
  "domain": "practice",
  "version": "1.0.0",
  "status": "draft",
  "description": "C1.1 Practice Definition registry — action types (not content). Variants are a separate layer.",
  "practice_definitions": {
    "breathing": {
      "code": "breathing",
      "category": "breathing",
      "title": "Breathing",
      "description": "Conscious breath regulation to shift state and anchor attention.",
      "effort_level": "low",
      "reflection_level": "low",
      "duration_range": { "min_minutes": 1, "max_minutes": 15 },
      "compatible_paths": ["discipline", "energy", "body", "clarity", "healing"],
      "compatible_stages": ["seeker", "observer", "practitioner", "explorer", "architect", "mentor", "master"],
      "produces_signals": ["practice_completed"],
      "contraindications": ["respiratory_distress", "hyperventilation_risk"],
      "status": "active",
      "version": "1.0.0"
    },
    "journaling": {
      "code": "journaling",
      "category": "journaling",
      "title": "Journaling",
      "description": "Structured or free-form written capture of experience, intent, or insight.",
      "effort_level": "low",
      "reflection_level": "medium",
      "duration_range": { "min_minutes": 3, "max_minutes": 30 },
      "compatible_paths": ["clarity", "creativity", "relationships", "purpose", "healing"],
      "compatible_stages": ["seeker", "observer", "practitioner", "explorer", "architect", "mentor", "master"],
      "produces_signals": ["practice_completed"],
      "contraindications": [],
      "status": "active",
      "version": "1.0.0"
    },
    "reflection": {
      "code": "reflection",
      "category": "reflection",
      "title": "Reflection",
      "description": "Review of the day, patterns, or emotional state with intentional closure.",
      "effort_level": "low",
      "reflection_level": "high",
      "duration_range": { "min_minutes": 3, "max_minutes": 20 },
      "compatible_paths": ["clarity", "relationships", "healing", "spirituality", "creativity"],
      "compatible_stages": ["observer", "practitioner", "explorer", "architect", "mentor", "master"],
      "produces_signals": ["practice_completed", "evening_reflection_confirmed"],
      "contraindications": ["acute_distress_without_support"],
      "status": "active",
      "version": "1.0.0"
    },
    "meditation": {
      "code": "meditation",
      "category": "meditation",
      "title": "Meditation",
      "description": "Sustained attention or open awareness practice without narrative output.",
      "effort_level": "medium",
      "reflection_level": "medium",
      "duration_range": { "min_minutes": 3, "max_minutes": 45 },
      "compatible_paths": ["discipline", "clarity", "energy", "spirituality", "healing"],
      "compatible_stages": ["seeker", "observer", "practitioner", "explorer", "architect", "mentor", "master"],
      "produces_signals": ["practice_completed"],
      "contraindications": ["dissociation_risk"],
      "status": "active",
      "version": "1.0.0"
    },
    "visualization": {
      "code": "visualization",
      "category": "visualization",
      "title": "Visualization",
      "description": "Guided or self-directed mental imagery toward a chosen state or outcome.",
      "effort_level": "medium",
      "reflection_level": "medium",
      "duration_range": { "min_minutes": 3, "max_minutes": 20 },
      "compatible_paths": ["clarity", "purpose", "creativity", "energy", "spirituality"],
      "compatible_stages": ["observer", "practitioner", "explorer", "architect", "mentor", "master"],
      "produces_signals": ["practice_completed"],
      "contraindications": ["dissociation_risk"],
      "status": "active",
      "version": "1.0.0"
    },
    "body_activation": {
      "code": "body_activation",
      "category": "body_activation",
      "title": "Body activation",
      "description": "Somatic movement or activation to restore energy, mobility, or grounding.",
      "effort_level": "medium",
      "reflection_level": "low",
      "duration_range": { "min_minutes": 3, "max_minutes": 30 },
      "compatible_paths": ["body", "energy", "discipline"],
      "compatible_stages": ["seeker", "observer", "practitioner", "explorer", "architect"],
      "produces_signals": ["practice_completed"],
      "contraindications": ["acute_injury", "medical_movement_restriction"],
      "status": "active",
      "version": "1.0.0"
    },
    "gratitude": {
      "code": "gratitude",
      "category": "gratitude",
      "title": "Gratitude",
      "description": "Explicit acknowledgment of what supports, nourishes, or went well.",
      "effort_level": "low",
      "reflection_level": "medium",
      "duration_range": { "min_minutes": 1, "max_minutes": 10 },
      "compatible_paths": ["relationships", "healing", "spirituality", "clarity"],
      "compatible_stages": ["seeker", "observer", "practitioner", "explorer", "architect", "mentor", "master"],
      "produces_signals": ["practice_completed"],
      "contraindications": [],
      "status": "active",
      "version": "1.0.0"
    },
    "attention_training": {
      "code": "attention_training",
      "category": "attention_training",
      "title": "Attention training",
      "description": "Deliberate exercises to strengthen focus, noticing, or cognitive presence.",
      "effort_level": "medium",
      "reflection_level": "low",
      "duration_range": { "min_minutes": 2, "max_minutes": 15 },
      "compatible_paths": ["discipline", "clarity", "energy"],
      "compatible_stages": ["observer", "practitioner", "explorer", "architect", "mentor", "master"],
      "produces_signals": ["practice_completed"],
      "contraindications": [],
      "status": "active",
      "version": "1.0.0"
    },
    "planning": {
      "code": "planning",
      "category": "planning",
      "title": "Planning",
      "description": "Structuring intent, priorities, or next actions for a day or horizon.",
      "effort_level": "low",
      "reflection_level": "medium",
      "duration_range": { "min_minutes": 3, "max_minutes": 25 },
      "compatible_paths": ["clarity", "purpose", "discipline", "wealth"],
      "compatible_stages": ["observer", "practitioner", "explorer", "architect", "mentor", "master"],
      "produces_signals": ["practice_completed"],
      "contraindications": [],
      "status": "active",
      "version": "1.0.0"
    },
    "self_observation": {
      "code": "self_observation",
      "category": "self_observation",
      "title": "Self observation",
      "description": "Noticing internal state, triggers, or reactions without immediate change agenda.",
      "effort_level": "low",
      "reflection_level": "high",
      "duration_range": { "min_minutes": 2, "max_minutes": 15 },
      "compatible_paths": ["clarity", "healing", "relationships", "spirituality"],
      "compatible_stages": ["observer", "practitioner", "explorer", "architect", "mentor", "master"],
      "produces_signals": ["practice_completed"],
      "contraindications": ["acute_distress_without_support"],
      "status": "active",
      "version": "1.0.0"
    }
  }
}
